collective.nitf-2.1.0-py2.7-nspkg.pth
collective/nitf/__init__.py
collective/nitf/adapters.py
collective/nitf/config.py
collective/nitf/configure.zcml
collective/nitf/content.py
collective/nitf/controlpanel.py
collective/nitf/dependencies.zcml
collective/nitf/interfaces.py
collective/nitf/logger.py
collective/nitf/profiles.zcml
collective/nitf/setuphandlers.py
collective/nitf/testing.py
collective/nitf/utils.py
collective/nitf/vocabulary.py
collective/nitf/vocabulary.zcml
collective/nitf/behaviors/__init__.py
collective/nitf/behaviors/configure.zcml
collective/nitf/behaviors/interfaces.py
collective/nitf/browser/__init__.py
collective/nitf/browser/configure.zcml
collective/nitf/browser/newsml.py
collective/nitf/browser/nitf.py
collective/nitf/browser/scaling.py
collective/nitf/browser/templates/document_byline.pt
collective/nitf/browser/templates/image.pt
collective/nitf/browser/templates/keywords.pt
collective/nitf/browser/templates/media.pt
collective/nitf/browser/templates/newsml.pt
collective/nitf/browser/templates/nitf.pt
collective/nitf/browser/templates/slideshow.pt
collective/nitf/browser/templates/view.pt
collective/nitf/locales/collective.nitf.pot
collective/nitf/locales/manual.pot
collective/nitf/locales/plone.pot
collective/nitf/locales/es/LC_MESSAGES/collective.nitf.mo
collective/nitf/locales/es/LC_MESSAGES/collective.nitf.po
collective/nitf/locales/es/LC_MESSAGES/plone.mo
collective/nitf/locales/es/LC_MESSAGES/plone.po
collective/nitf/locales/pt_BR/LC_MESSAGES/collective.nitf.mo
collective/nitf/locales/pt_BR/LC_MESSAGES/collective.nitf.po
collective/nitf/locales/pt_BR/LC_MESSAGES/plone.mo
collective/nitf/locales/pt_BR/LC_MESSAGES/plone.po
collective/nitf/portlets/__init__.py
collective/nitf/portlets/configure.zcml
collective/nitf/portlets/latest_sectionable_nitf.py
collective/nitf/profiles/default/browserlayer.xml
collective/nitf/profiles/default/catalog.xml
collective.nitf-2.1.0.dist-info/DESCRIPTION.rst
collective.nitf-2.1.0.dist-info/METADATA
collective.nitf-2.1.0.dist-info/RECORD
collective.nitf-2.1.0.dist-info/WHEEL
collective.nitf-2.1.0.dist-info/entry_points.txt
collective.nitf-2.1.0.dist-info/metadata.json
collective.nitf-2.1.0.dist-info/namespace_packages.txt
collective.nitf-2.1.0.dist-info/top_level.txt
