Metadata-Version: 2.0
Name: collective.nitf
Version: 2.1.0
Summary: A content type inspired on the IPTC's News Industry Text Format specification.
Home-page: https://github.com/collective/collective.nitf
Author: Hector Velarde
Author-email: hector.velarde@gmail.com
License: UNKNOWN
Keywords: plone dexterity iptc newsml nitf
Platform: UNKNOWN
Classifier: Development Status :: 4 - Beta
Classifier: Environment :: Web Environment
Classifier: Framework :: Plone
Classifier: Framework :: Plone :: 4.3
Classifier: Framework :: Plone :: Addon
Classifier: Intended Audience :: End Users/Desktop
Classifier: Intended Audience :: System Administrators
Classifier: License :: OSI Approved :: GNU General Public License v2 (GPLv2)
Classifier: Operating System :: OS Independent
Classifier: Programming Language :: JavaScript
Classifier: Programming Language :: Python
Classifier: Programming Language :: Python :: 2.7
Classifier: Topic :: Office/Business :: News/Diary
Classifier: Topic :: Software Development :: Libraries :: Python Modules
Provides-Extra: test
Requires-Dist: Acquisition
Requires-Dist: collective.js.jqueryui
Requires-Dist: collective.prettydate (>=1.1)
Requires-Dist: plone.api
Requires-Dist: plone.app.content
Requires-Dist: plone.app.contentmenu
Requires-Dist: plone.app.dexterity[relations]
Requires-Dist: plone.app.imaging
Requires-Dist: plone.app.layout (>=2.3.12)
Requires-Dist: plone.app.lockingbehavior
Requires-Dist: plone.app.portlets
Requires-Dist: plone.app.registry
Requires-Dist: plone.app.relationfield
Requires-Dist: plone.app.textfield
Requires-Dist: plone.app.upgrade
Requires-Dist: plone.app.vocabularies
Requires-Dist: plone.autoform
Requires-Dist: plone.behavior
Requires-Dist: plone.dexterity
Requires-Dist: plone.formwidget.autocomplete
Requires-Dist: plone.formwidget.contenttree
Requires-Dist: plone.indexer
Requires-Dist: plone.memoize
Requires-Dist: plone.portlets
Requires-Dist: plone.registry
Requires-Dist: plone.supermodel
Requires-Dist: plone.uuid
Requires-Dist: Products.CMFPlone (>=4.3)
Requires-Dist: Products.CMFQuickInstallerTool
Requires-Dist: Products.GenericSetup
Requires-Dist: setuptools
Requires-Dist: zope.browserpage
Requires-Dist: zope.component
Requires-Dist: zope.deprecation
Requires-Dist: zope.i18nmessageid
Requires-Dist: zope.interface
Requires-Dist: zope.schema
Provides-Extra: test
Requires-Dist: AccessControl; extra == 'test'
Requires-Dist: lxml; extra == 'test'
Requires-Dist: mock; extra == 'test'
Requires-Dist: plone.app.customerize; extra == 'test'
Requires-Dist: plone.app.robotframework; extra == 'test'
Requires-Dist: plone.app.testing[robot]; extra == 'test'
Requires-Dist: plone.browserlayer; extra == 'test'
Requires-Dist: plone.namedfile; extra == 'test'
Requires-Dist: plone.testing; extra == 'test'
Requires-Dist: robotsuite; extra == 'test'
Requires-Dist: six; extra == 'test'
Requires-Dist: z3c.relationfield; extra == 'test'
Requires-Dist: zope.intid; extra == 'test'
Requires-Dist: zope.viewlet; extra == 'test'
